{
"meta":{"test_sets":[],"test_metrics":[],"learn_metrics":[{"best_value":"Min","name":"RMSE"}],"launch_mode":"Train","parameters":"","iteration_count":100,"learn_sets":["learn"],"name":"experiment"},
"iterations":[
{"learn":[14.005006],"iteration":0,"passed_time":0.0008133548823,"remaining_time":0.08052213335},
{"learn":[13.14441192],"iteration":1,"passed_time":0.001519071655,"remaining_time":0.07443451112},
{"learn":[12.34258257],"iteration":2,"passed_time":0.002197623098,"remaining_time":0.07105648016},
{"learn":[11.64527793],"iteration":3,"passed_time":0.002826669035,"remaining_time":0.06784005684},
{"learn":[11.02766183],"iteration":4,"passed_time":0.003543059336,"remaining_time":0.06731812738},
{"learn":[10.43485794],"iteration":5,"passed_time":0.004195719449,"remaining_time":0.06573293804},
{"learn":[9.890641275],"iteration":6,"passed_time":0.004840534921,"remaining_time":0.06430996395},
{"learn":[9.492161212],"iteration":7,"passed_time":0.005488801233,"remaining_time":0.06312121418},
{"learn":[9.105082953],"iteration":8,"passed_time":0.006145845116,"remaining_time":0.06214132284},
{"learn":[8.674157135],"iteration":9,"passed_time":0.006804092781,"remaining_time":0.06123683503},
{"learn":[8.341743544],"iteration":10,"passed_time":0.007485292542,"remaining_time":0.06056282148},
{"learn":[8.049372916],"iteration":11,"passed_time":0.008187177279,"remaining_time":0.06003930004},
{"learn":[7.757318612],"iteration":12,"passed_time":0.008866842219,"remaining_time":0.05933963639},
{"learn":[7.522206899],"iteration":13,"passed_time":0.009567031629,"remaining_time":0.05876890858},
{"learn":[7.297756655],"iteration":14,"passed_time":0.01028153601,"remaining_time":0.05826203737},
{"learn":[7.088359431],"iteration":15,"passed_time":0.01097494412,"remaining_time":0.05761845661},
{"learn":[6.882113791],"iteration":16,"passed_time":0.01168952874,"remaining_time":0.05707240504},
{"learn":[6.704728832],"iteration":17,"passed_time":0.01237916501,"remaining_time":0.05639397391},
{"learn":[6.563881962],"iteration":18,"passed_time":0.01308453068,"remaining_time":0.05578142025},
{"learn":[6.418790279],"iteration":19,"passed_time":0.01380959823,"remaining_time":0.05523839293},
{"learn":[6.315756953],"iteration":20,"passed_time":0.01450336748,"remaining_time":0.05456028718},
{"learn":[6.210157751],"iteration":21,"passed_time":0.01518469765,"remaining_time":0.0538366553},
{"learn":[6.115058449],"iteration":22,"passed_time":0.01587953023,"remaining_time":0.05316190556},
{"learn":[6.014819884],"iteration":23,"passed_time":0.0166857828,"remaining_time":0.05283831222},
{"learn":[5.93117229],"iteration":24,"passed_time":0.01742981995,"remaining_time":0.05228945985},
{"learn":[5.844857622],"iteration":25,"passed_time":0.01818342715,"remaining_time":0.05175283113},
{"learn":[5.771145213],"iteration":26,"passed_time":0.01889426,"remaining_time":0.05108448073},
{"learn":[5.704018229],"iteration":27,"passed_time":0.01959690713,"remaining_time":0.0503920469},
{"learn":[5.665806474],"iteration":28,"passed_time":0.02031002716,"remaining_time":0.04972454924},
{"learn":[5.616500369],"iteration":29,"passed_time":0.02104401273,"remaining_time":0.04910269636},
{"learn":[5.558023666],"iteration":30,"passed_time":0.02176739499,"remaining_time":0.0484500082},
{"learn":[5.510080976],"iteration":31,"passed_time":0.02248771764,"remaining_time":0.04778639999},
{"learn":[5.468747792],"iteration":32,"passed_time":0.02320977575,"remaining_time":0.04712287803},
{"learn":[5.429275534],"iteration":33,"passed_time":0.02394464409,"remaining_time":0.0464807797},
{"learn":[5.402117324],"iteration":34,"passed_time":0.02467884032,"remaining_time":0.04583213202},
{"learn":[5.367635151],"iteration":35,"passed_time":0.0254234292,"remaining_time":0.04519720746},
{"learn":[5.345181232],"iteration":36,"passed_time":0.02615590001,"remaining_time":0.04453572164},
{"learn":[5.319151269],"iteration":37,"passed_time":0.02690879498,"remaining_time":0.04390382338},
{"learn":[5.296134146],"iteration":38,"passed_time":0.02766478968,"remaining_time":0.04327056848},
{"learn":[5.269629003],"iteration":39,"passed_time":0.02839481281,"remaining_time":0.04259221921},
{"learn":[5.251147059],"iteration":40,"passed_time":0.02913885998,"remaining_time":0.04193153022},
{"learn":[5.248003302],"iteration":41,"passed_time":0.02946578691,"remaining_time":0.04069084859},
{"learn":[5.232376509],"iteration":42,"passed_time":0.03017988,"remaining_time":0.04000588744},
{"learn":[5.213524255],"iteration":43,"passed_time":0.03123203499,"remaining_time":0.03974986271},
{"learn":[5.189691584],"iteration":44,"passed_time":0.03213850235,"remaining_time":0.03928039177},
{"learn":[5.166052198],"iteration":45,"passed_time":0.03294976065,"remaining_time":0.03868015381},
{"learn":[5.140406659],"iteration":46,"passed_time":0.03373397399,"remaining_time":0.03804043876},
{"learn":[5.118929684],"iteration":47,"passed_time":0.03451955162,"remaining_time":0.03739618093},
{"learn":[5.108792602],"iteration":48,"passed_time":0.03528912899,"remaining_time":0.03672950161},
{"learn":[5.098141225],"iteration":49,"passed_time":0.03604067974,"remaining_time":0.03604067974},
{"learn":[5.085926393],"iteration":50,"passed_time":0.03679812901,"remaining_time":0.03535506513},
{"learn":[5.067816804],"iteration":51,"passed_time":0.03756160722,"remaining_time":0.03467225282},
{"learn":[5.049834901],"iteration":52,"passed_time":0.03832634941,"remaining_time":0.0339875174},
{"learn":[5.03838627],"iteration":53,"passed_time":0.0391221993,"remaining_time":0.03332631792},
{"learn":[5.033534248],"iteration":54,"passed_time":0.03964423912,"remaining_time":0.03243619564},
{"learn":[5.023726885],"iteration":55,"passed_time":0.04040031407,"remaining_time":0.03174310391},
{"learn":[5.01290392],"iteration":56,"passed_time":0.04117280058,"remaining_time":0.03106018289},
{"learn":[5.005569127],"iteration":57,"passed_time":0.04192134187,"remaining_time":0.03035683377},
{"learn":[4.989969032],"iteration":58,"passed_time":0.04269797139,"remaining_time":0.02967147165},
{"learn":[4.976762446],"iteration":59,"passed_time":0.04345037482,"remaining_time":0.02896691654},
{"learn":[4.967222715],"iteration":60,"passed_time":0.04426784262,"remaining_time":0.02830239118},
{"learn":[4.954407599],"iteration":61,"passed_time":0.04508014419,"remaining_time":0.0276297658},
{"learn":[4.942125056],"iteration":62,"passed_time":0.04582647855,"remaining_time":0.02691396359},
{"learn":[4.930230716],"iteration":63,"passed_time":0.04659884468,"remaining_time":0.02621185013},
{"learn":[4.921695642],"iteration":64,"passed_time":0.0473742303,"remaining_time":0.02550920093},
{"learn":[4.906405625],"iteration":65,"passed_time":0.04815068928,"remaining_time":0.02480490054},
{"learn":[4.894330248],"iteration":66,"passed_time":0.04890273157,"remaining_time":0.02408642003},
{"learn":[4.88211557],"iteration":67,"passed_time":0.04965970936,"remaining_time":0.023369275},
{"learn":[4.877946398],"iteration":68,"passed_time":0.05042107093,"remaining_time":0.02265294491},
{"learn":[4.863182126],"iteration":69,"passed_time":0.05121431263,"remaining_time":0.02194899113},
{"learn":[4.84646533],"iteration":70,"passed_time":0.052061885,"remaining_time":0.02126471359},
{"learn":[4.838014752],"iteration":71,"passed_time":0.05294801849,"remaining_time":0.02059089608},
{"learn":[4.82981137],"iteration":72,"passed_time":0.05382207404,"remaining_time":0.01990679451},
{"learn":[4.817094767],"iteration":73,"passed_time":0.05470780627,"remaining_time":0.01922166166},
{"learn":[4.808314151],"iteration":74,"passed_time":0.05549570118,"remaining_time":0.01849856706},
{"learn":[4.796235023],"iteration":75,"passed_time":0.0562745577,"remaining_time":0.01777091296},
{"learn":[4.784434534],"iteration":76,"passed_time":0.05702745267,"remaining_time":0.01703417417},
{"learn":[4.774402487],"iteration":77,"passed_time":0.05778709884,"remaining_time":0.01629892531},
{"learn":[4.76731896],"iteration":78,"passed_time":0.05861278245,"remaining_time":0.01558061306},
{"learn":[4.75934113],"iteration":79,"passed_time":0.05937448508,"remaining_time":0.01484362127},
{"learn":[4.754106378],"iteration":80,"passed_time":0.06011787018,"remaining_time":0.01410172263},
{"learn":[4.744002932],"iteration":81,"passed_time":0.06087032376,"remaining_time":0.01336177839},
{"learn":[4.731700554],"iteration":82,"passed_time":0.06162769278,"remaining_time":0.01262253949},
{"learn":[4.723284153],"iteration":83,"passed_time":0.06236410598,"remaining_time":0.01187887733},
{"learn":[4.712232782],"iteration":84,"passed_time":0.06313159679,"remaining_time":0.01114087002},
{"learn":[4.703046867],"iteration":85,"passed_time":0.06388594633,"remaining_time":0.01040003777},
{"learn":[4.698601855],"iteration":86,"passed_time":0.06464926404,"remaining_time":0.009660234856},
{"learn":[4.692429407],"iteration":87,"passed_time":0.06541732665,"remaining_time":0.008920544543},
{"learn":[4.675027364],"iteration":88,"passed_time":0.06617070313,"remaining_time":0.00817840151},
{"learn":[4.662368584],"iteration":89,"passed_time":0.06693285718,"remaining_time":0.007436984131},
{"learn":[4.646206172],"iteration":90,"passed_time":0.06769664637,"remaining_time":0.006695272718},
{"learn":[4.641245848],"iteration":91,"passed_time":0.06842905699,"remaining_time":0.005950352782},
{"learn":[4.633900435],"iteration":92,"passed_time":0.06919733026,"remaining_time":0.005208401203},
{"learn":[4.624738236],"iteration":93,"passed_time":0.06995576263,"remaining_time":0.004465261444},
{"learn":[4.612798287],"iteration":94,"passed_time":0.07071752545,"remaining_time":0.003721975024},
{"learn":[4.605222001],"iteration":95,"passed_time":0.07147534589,"remaining_time":0.002978139412},
{"learn":[4.601725912],"iteration":96,"passed_time":0.07240667038,"remaining_time":0.002239381558},
{"learn":[4.59722371],"iteration":97,"passed_time":0.07339783474,"remaining_time":0.001497914995},
{"learn":[4.580235665],"iteration":98,"passed_time":0.07419648343,"remaining_time":0.0007494594286},
{"learn":[4.57591791],"iteration":99,"passed_time":0.0749447639,"remaining_time":0}
]}